README.txt
setup.py
ckanext/__init__.py
ckanext/wordpresser/__init__.py
ckanext/wordpresser/middleware.py
ckanext_wordpresser.egg-info/PKG-INFO
ckanext_wordpresser.egg-info/SOURCES.txt
ckanext_wordpresser.egg-info/dependency_links.txt
ckanext_wordpresser.egg-info/entry_points.txt
ckanext_wordpresser.egg-info/namespace_packages.txt
ckanext_wordpresser.egg-info/not-zip-safe
ckanext_wordpresser.egg-info/requires.txt
ckanext_wordpresser.egg-info/top_level.txt