Metadata-Version: 1.0
Name: ckanext-wordpresser
Version: 0.1
Summary: Extend CKAN content with content from Wordpress
Home-page: UNKNOWN
Author: Seb Bacon
Author-email: seb.bacon@okfn.org
License: GPL
Keywords: wordpress wsgi middleware ckan
Platform: UNKNOWN
Classifier: Development Status :: 2 - Pre-Alpha
Classifier: Framework :: Pylons
